invenio_search/__init__.py
invenio_search/api.py
invenio_search/cli.py
invenio_search/config.py
invenio_search/engine.py
invenio_search/errors.py
invenio_search/ext.py
invenio_search/proxies.py
invenio_search/utils.py
invenio_search-3.1.1.dist-info/licenses/AUTHORS.rst
invenio_search-3.1.1.dist-info/licenses/LICENSE
invenio_search-3.1.1.dist-info/METADATA
invenio_search-3.1.1.dist-info/WHEEL
invenio_search-3.1.1.dist-info/entry_points.txt
invenio_search-3.1.1.dist-info/top_level.txt
invenio_search-3.1.1.dist-info/RECORD
