Metadata-Version: 2.4
Name: invenio-search
Version: 3.1.1
Summary: "Invenio module for information retrieval."
Home-page: https://github.com/inveniosoftware/invenio-search
Author: CERN
Author-email: info@inveniosoftware.org
License: MIT
Keywords: invenio search
Platform: any
Classifier: Development Status :: 5 - Production/Stable
Requires-Python: >=3.7
License-File: LICENSE
License-File: AUTHORS.rst
Requires-Dist: invenio-base<3.0.0,>=2.0.0
Requires-Dist: dictdiffer>=0.9.0
Provides-Extra: tests
Requires-Dist: pytest-black-ng>=0.4.0; extra == "tests"
Requires-Dist: invenio-db[versioning]<3.0.0,>=2.0.0; extra == "tests"
Requires-Dist: mock>=1.3.0; extra == "tests"
Requires-Dist: pytest-invenio<4.0.0,>=3.0.0; extra == "tests"
Requires-Dist: Sphinx>=3; extra == "tests"
Requires-Dist: invenio-accounts<7.0.0,>=6.0.0; extra == "tests"
Provides-Extra: elasticsearch7
Requires-Dist: elasticsearch<7.14,>=7.0.0; extra == "elasticsearch7"
Requires-Dist: elasticsearch-dsl<8.0.0,>=7.0.0; extra == "elasticsearch7"
Provides-Extra: opensearch1
Requires-Dist: opensearch-py<2.0.0,>=1.1.0; extra == "opensearch1"
Requires-Dist: opensearch-dsl<2.0.0,>=1.0.0; extra == "opensearch1"
Provides-Extra: opensearch2
Requires-Dist: opensearch-py<3.0.0,>=2.0.0; extra == "opensearch2"
Requires-Dist: opensearch-dsl<3.0.0,>=2.0.0; extra == "opensearch2"
Dynamic: license-file
